price_action_lib/__init__.py
price_action_lib/main.py
price_action_lib/analysis/__init__.py
price_action_lib/analysis/gap_analysis.py
price_action_lib/analysis/multi_timeframe.py
price_action_lib/analysis/session_analysis.py
price_action_lib/analysis/volume_analysis.py
price_action_lib/core/__init__.py
price_action_lib/core/base.py
price_action_lib/core/timeframe.py
price_action_lib/patterns/__init__.py
price_action_lib/patterns/candlestick.py
price_action_lib/patterns/chart_patterns.py
price_action_lib/structures/__init__.py
price_action_lib/structures/market_structure.py
price_action_lib/structures/support_resistance.py
price_action_lib-1.0.1.dist-info/licenses/LICENSE
price_action_lib-1.0.1.dist-info/METADATA
price_action_lib-1.0.1.dist-info/WHEEL
price_action_lib-1.0.1.dist-info/top_level.txt
price_action_lib-1.0.1.dist-info/RECORD
