Metadata-Version: 2.4
Name: price-action-lib
Version: 1.0.1
Summary: A comprehensive price action analysis library for Indian stock market
Home-page: https://github.com/nashit8421/price-action-lib
Author: Nashit
Author-email: Nashit <nashit8421@gmail.com>
License: MIT License
Project-URL: Homepage, https://github.com/nashit8421/price-action-lib
Project-URL: Documentation, https://github.com/nashit8421/price-action-lib#readme
Project-URL: Repository, https://github.com/nashit8421/price-action-lib.git
Project-URL: Issues, https://github.com/nashit8421/price-action-lib/issues
Keywords: price action,trading,stock market,candlestick patterns,technical analysis,indian stocks,NSE,BSE
Classifier: Development Status :: 5 - Production/Stable
Classifier: Intended Audience :: Financial and Insurance Industry
Classifier: Intended Audience :: Developers
Classifier: Topic :: Office/Business :: Financial :: Investment
Classifier: Topic :: Scientific/Engineering :: Information Analysis
Classifier: License :: OSI Approved :: MIT License
Classifier: Programming Language :: Python :: 3
Classifier: Programming Language :: Python :: 3.7
Classifier: Programming Language :: Python :: 3.8
Classifier: Programming Language :: Python :: 3.9
Classifier: Programming Language :: Python :: 3.10
Classifier: Programming Language :: Python :: 3.11
Classifier: Programming Language :: Python :: 3.12
Classifier: Operating System :: OS Independent
Requires-Python: >=3.7
License-File: LICENSE
Requires-Dist: pandas>=1.3.0
Requires-Dist: numpy>=1.21.0
Requires-Dist: scipy>=1.7.0
Provides-Extra: dev
Requires-Dist: pytest>=7.0.0; extra == "dev"
Requires-Dist: pytest-cov>=3.0.0; extra == "dev"
Requires-Dist: black>=22.0.0; extra == "dev"
Requires-Dist: flake8>=4.0.0; extra == "dev"
Dynamic: author
Dynamic: home-page
Dynamic: license-file
Dynamic: requires-python
